cleo/__init__.py
cleo/base.py
cleo/coords.py
cleo/ephys/__init__.py
cleo/ephys/lfp.py
cleo/ephys/probes.py
cleo/ephys/spiking.py
cleo/imaging/__init__.py
cleo/imaging/scope.py
cleo/imaging/sensors.py
cleo/ioproc.py
cleo/light/__init__.py
cleo/light/light.py
cleo/light/light_dependence.py
cleo/light/two_photon.py
cleo/net.pkl
cleo/netstore.pkl
cleo/opto/__init__.py
cleo/opto/opsin_library.py
cleo/opto/opsins.py
cleo/recorders.py
cleo/registry.py
cleo/stimulators.py
cleo/test_store.py
cleo/utilities.py
cleo/viz.py
cleosim-0.18.2.dist-info/LICENSE
cleosim-0.18.2.dist-info/METADATA
cleosim-0.18.2.dist-info/WHEEL
cleosim-0.18.2.dist-info/RECORD
