Metadata-Version: 2.3
Name: cleosim
Version: 0.18.2
Summary: Cleo: the Closed-Loop, Electrophysiology, and Optophysiology experiment simulation testbed
License: MIT
Author: Kyle Johnsen
Author-email: kyle@kjohnsen.org
Requires-Python: >=3.10,<3.14
Classifier: Development Status :: 4 - Beta
Classifier: Intended Audience :: Science/Research
Classifier: License :: OSI Approved :: MIT License
Classifier: Programming Language :: Python :: 3
Classifier: Programming Language :: Python :: 3.10
Classifier: Programming Language :: Python :: 3.11
Classifier: Programming Language :: Python :: 3.12
Classifier: Programming Language :: Python :: 3.13
Provides-Extra: dev
Requires-Dist: attrs (>=23.0,<24.0)
Requires-Dist: brian2 (>=2.4,!=2.5.0.2,<3.0.0)
Requires-Dist: cvxpy (>=1.6.5,<2.0.0) ; extra == "dev"
Requires-Dist: furo (>=2024.1.29,<2025.0.0) ; extra == "dev"
Requires-Dist: jaxtyping (>=0.2.34,<0.3.0)
Requires-Dist: marimo (>=0.11.20,<1.0.0) ; extra == "dev"
Requires-Dist: matplotlib (>=3.7,<4.0.0)
Requires-Dist: myst-nb (>=1.0,<2.0) ; extra == "dev"
Requires-Dist: nbdev (>=2.3.12,<3.0.0) ; extra == "dev"
Requires-Dist: nbmake (>=1.2,<2.0.0) ; extra == "dev"
Requires-Dist: neo (>=0.12.0,<0.13.0)
Requires-Dist: numpy (>=2.1.0,<3.0.0) ; python_version >= "3.13"
Requires-Dist: pytest (>=7.0.0,<8.0.0) ; extra == "dev"
Requires-Dist: pytest-xdist (>=3.5.0,<4.0.0) ; extra == "dev"
Requires-Dist: ruff (>=0.1.15,<1.0.0) ; extra == "dev"
Requires-Dist: scipy (>=1.14.1) ; python_version >= "3.13"
Requires-Dist: scipy (>=1.7.2,<1.14.1) ; python_version < "3.13"
Requires-Dist: seaborn (>=0.13.0,<0.14.0) ; extra == "dev"
Requires-Dist: sphinx (>=7.0,<8.0) ; extra == "dev"
Requires-Dist: sphinx-copybutton (>=0.5.2,<0.6.0) ; extra == "dev"
Requires-Dist: sphinx-favicon (>=0.2,<0.3) ; extra == "dev"
Requires-Dist: tklfp (>=0.2,<0.3)
Requires-Dist: wslfp (>=0.2.1,<0.3.0)
Project-URL: Documentation, https://cleosim.readthedocs.io/
Project-URL: source, https://github.com/siplab-gt/cleo/
